nlp_mitb_2025/__init__.py
nlp_mitb_2025/lab1.py
nlp_mitb_2025/lab10.py
nlp_mitb_2025/lab2.py
nlp_mitb_2025/lab3.py
nlp_mitb_2025/lab4.py
nlp_mitb_2025/lab5.py
nlp_mitb_2025/lab6.py
nlp_mitb_2025/lab7.py
nlp_mitb_2025/lab8.py
nlp_mitb_2025/lab9.py
nlp_tools_library-0.1.0.dist-info/METADATA
nlp_tools_library-0.1.0.dist-info/WHEEL
nlp_tools_library-0.1.0.dist-info/top_level.txt
nlp_tools_library-0.1.0.dist-info/RECORD
