Metadata-Version: 2.4
Name: nlp_tools_library
Version: 0.1.0
Summary: A comprehensive NLP toolkit based on lab exercises
Author: Vedant Raikar
Author-email: vedantraikar117@gmail.com
Classifier: Programming Language :: Python :: 3
Classifier: License :: OSI Approved :: MIT License
Classifier: Operating System :: OS Independent
Requires-Python: >=3.6
Requires-Dist: nltk>=3.6.0
Requires-Dist: spacy>=3.0.0
Requires-Dist: scikit-learn>=0.24.0
Requires-Dist: hmmlearn>=0.2.5
Requires-Dist: regex>=2021.8.3
Dynamic: author
Dynamic: author-email
Dynamic: classifier
Dynamic: description
Dynamic: description-content-type
Dynamic: requires-dist
Dynamic: requires-python
Dynamic: summary
